sparkmeasure/__init__.py
sparkmeasure/jmx.py
sparkmeasure/stagemetrics.py
sparkmeasure/taskmetrics.py
sparkmeasure/test_jmx.py
sparkmeasure/test_stagemetrics.py
sparkmeasure/test_taskmetrics.py
sparkmeasure/testutils.py
sparkmeasure-0.27.0.dist-info/METADATA
sparkmeasure-0.27.0.dist-info/WHEEL
sparkmeasure-0.27.0.dist-info/top_level.txt
sparkmeasure-0.27.0.dist-info/RECORD
